LICENSE
MANIFEST.in
README.rst
setup.py
django_mail_save.egg-info/PKG-INFO
django_mail_save.egg-info/SOURCES.txt
django_mail_save.egg-info/dependency_links.txt
django_mail_save.egg-info/requires.txt
django_mail_save.egg-info/top_level.txt
mail_save/__init__.py
mail_save/admin.py
mail_save/models.py
mail_save/urls.py
mail_save/views.py
mail_save/backends/__init__.py
mail_save/backends/smtp.py
mail_save/migrations/0001_initial.py
mail_save/migrations/__init__.py
mail_save/templates/mail_save/email/alternative.html
mail_save/templates/mail_save/partials/iframe.html