Metadata-Version: 1.1
Name: django-mail-save
Version: 0.0.5
Summary: Save outgoing mail to the database
Home-page: https://github.com/bigmassa/django_mail_save
Author: Stuart George
Author-email: stuart.bigmassa@gmail.com
License: MIT
Keywords: mail,save,email,admin
Platform: UNKNOWN
Classifier: Development Status :: 4 - Beta
Classifier: Environment :: Web Environment
Classifier: Framework :: Django
Classifier: Intended Audience :: Developers
Classifier: License :: OSI Approved :: MIT License
Classifier: Operating System :: OS Independent
Classifier: Programming Language :: Python
Classifier: Programming Language :: Python :: 3.5
Classifier: Topic :: System :: Logging
Classifier: Topic :: Communications :: Email
